substack_api/__init__.py
substack_api/auth.py
substack_api/category.py
substack_api/newsletter.py
substack_api/post.py
substack_api/user.py
substack_api-1.1.1.dist-info/licenses/LICENSE
substack_api-1.1.1.dist-info/METADATA
substack_api-1.1.1.dist-info/WHEEL
substack_api-1.1.1.dist-info/top_level.txt
substack_api-1.1.1.dist-info/RECORD
