Metadata-Version: 2.4
Name: substack-api
Version: 1.1.1
Summary: Unofficial wrapper for the Substack API
Project-URL: Homepage, https://github.com/nhagar/substack_api
Project-URL: Bug Tracker, https://github.com/nhagar/substack_api/issues
Project-URL: Documentation, https://nhagar.github.io/substack_api/
Requires-Python: >=3.12
License-File: LICENSE
Requires-Dist: requests>=2.32.3
Dynamic: license-file
